metagit/__init__.py
metagit/__main__.py
metagit-1.4.0.dist-info/LICENSE
metagit-1.4.0.dist-info/METADATA
metagit-1.4.0.dist-info/WHEEL
metagit-1.4.0.dist-info/entry_points.txt
metagit-1.4.0.dist-info/top_level.txt
metagit-1.4.0.dist-info/RECORD
