Metadata-Version: 2.1
Name: metagit
Version: 1.4.0
Summary: A Git Project Manager
Home-page: https://github.com/dmtucker/metagit
Author: David Tucker
Author-email: david@tucker.name
License: LGPLv2+
Platform: UNKNOWN
Classifier: License :: OSI Approved :: GNU Lesser General Public License v2 or later (LGPLv2+)
Classifier: Intended Audience :: End Users/Desktop
Classifier: Programming Language :: Python :: 3.6
Classifier: Development Status :: 5 - Production/Stable
Requires-Python: >= 3.6
License-File: LICENSE
Requires-Dist: attrs (>=20.3)
Requires-Dist: click (>=7.1)
Requires-Dist: gitpython (>=3.1)
Requires-Dist: setuptools (>=49.6)
